akit/__init__.py
akit-0.0.1.dist-info/METADATA
akit-0.0.1.dist-info/WHEEL
akit-0.0.1.dist-info/entry_points.txt
akit-0.0.1.dist-info/top_level.txt
akit-0.0.1.dist-info/RECORD
